[
      {
        "name": "Alice Johnson",
        "preferred_job": "Software Engineer",
        "rank": 1
      },
      {
        "name": "Bob Smith",
        "preferred_job": "Data Scientist",
        "rank": 1
      },
      {
        "name": "Carol Davis",
        "preferred_job": "Product Manager",
        "rank": 1
      },
      {
        "name": "David Brown",
        "preferred_job": "Software Engineer",
        "rank": 2
      },
      {
        "name": "Eve Wilson",
        "preferred_job": "UX Designer",
        "rank": 2
      },
      {
        "name": "Frank Clark",
        "preferred_job": "DevOps Engineer",
        "rank": 3
      },
      {
        "name": "Grace Lee",
        "preferred_job": "Data Analyst",
        "rank": 7
      },
      {
        "name": "Hank Moore",
        "preferred_job": "Marketing Specialist",
        "rank": 8
      },
      {
        "name": "Ivy Taylor",
        "preferred_job": "HR Manager",
        "rank": 9
      },
      {
        "name": "Jack Anderson",
        "preferred_job": "Financial Analyst",
        "rank": 10
      },
      {
        "name": "Kimberly Harris",
        "preferred_job": "Software Engineer",
        "rank": 11
      },
      {
        "name": "Liam Martin",
        "preferred_job": "Data Scientist",
        "rank": 12
      },
      {
        "name": "Mia Rodriguez",
        "preferred_job": "Product Manager",
        "rank": 13
      },
      {
        "name": "Noah Martinez",
        "preferred_job": "Software Engineer",
        "rank": 14
      },
      {
        "name": "Olivia White",
        "preferred_job": "UX Designer",
        "rank": 15
      },
      {
        "name": "Paul King",
        "preferred_job": "DevOps Engineer",
        "rank": 16
      },
      {
        "name": "Quinn Perez",
        "preferred_job": "Data Analyst",
        "rank": 17
      },
      {
        "name": "Rachel Scott",
        "preferred_job": "Marketing Specialist",
        "rank": 18
      },
      {
        "name": "Sam Young",
        "preferred_job": "HR Manager",
        "rank": 19
      },
      {
        "name": "Tina Hill",
        "preferred_job": "Financial Analyst",
        "rank": 20
      }
    ]
  